[
  {
    "found": "2020-12-19T19:47:41.444Z", 
    "needs": "Cartons Fruit Juice - Long Life - No Stock\r\nDog Food - Wet And Dry - No Stock\r\nEggs\r\nSponge Puddings/slab Cake\r\nCustard And Rice Pudding\r\nToilet Rolls\r\nTinned Spaghetti\r\nTins Of Sardines/mackerel\r\nTinned Ham And Chicken\r\nWashing Powder/tabs/detergent\r\nLocal Supermarket Gift Cards/vouchers - Morrisons/lidl/aldi/asda/sainsbury's", 
    "id": "4e8e0510", 
    "foodbank": {
      "name": "Market Drayton", 
      "urls": {
        "self": "https://www.givefood.org.uk/api/2/foodbank/market-drayton/", 
        "html": "https://www.givefood.org.uk/needs/at/market-drayton/"
      }, 
      "slug": "market-drayton"
    }, 
    "self": "https://www.givefood.org.uk/api/2/needs/4e8e0510/"
  }, 
  {
    "found": "2020-12-19T19:09:51.870Z", 
    "needs": "Nothing", 
    "id": "2198c1a8", 
    "foodbank": {
      "name": "Harold Hill", 
      "urls": {
        "self": "https://www.givefood.org.uk/api/2/foodbank/harold-hill/", 
        "html": "https://www.givefood.org.uk/needs/at/harold-hill/"
      }, 
      "slug": "harold-hill"
    }, 
    "self": "https://www.givefood.org.uk/api/2/needs/2198c1a8/"
  }, 
  {
    "found": "2020-12-19T14:07:37.832Z", 
    "needs": "Fruit (Tinned)\r\nPotatoes (Tinned)\r\nPowdered Milk\r\nSponge Puddings\r\nSugar\r\nMashed Potato (Packets)\r\nRice Pudding (Tinned)\r\nToiletries & Shampoo/conditioner\r\nWashing Powder", 
    "id": "443b0ef2", 
    "foodbank": {
      "name": "Waterside", 
      "urls": {
        "self": "https://www.givefood.org.uk/api/2/foodbank/waterside/", 
        "html": "https://www.givefood.org.uk/needs/at/waterside/"
      }, 
      "slug": "waterside"
    }, 
    "self": "https://www.givefood.org.uk/api/2/needs/443b0ef2/"
  }, 
  {
    "found": "2020-12-19T12:06:33.736Z", 
    "needs": "Tinned Potatoes\r\nBags For Life\r\nTinned Ready Meals\r\nTinned Ham / Corned Beef\r\nTinned Fruit", 
    "id": "3b1e4b46", 
    "foodbank": {
      "name": "St Ives", 
      "urls": {
        "self": "https://www.givefood.org.uk/api/2/foodbank/st-ives/", 
        "html": "https://www.givefood.org.uk/needs/at/st-ives/"
      }, 
      "slug": "st-ives"
    }, 
    "self": "https://www.givefood.org.uk/api/2/needs/3b1e4b46/"
  }, 
  {
    "found": "2020-12-19T08:02:47.683Z", 
    "needs": "Tinned Potatoes\r\nTinned Carrots\r\nJam\r\nPorridge\r\nSmall Boxes Of Washing Pods / Gel\r\nSmall Packs Of Sugar\r\nAny Unwanted Pet Food\r\nStrong Carrier Bags", 
    "id": "96dcaf64", 
    "foodbank": {
      "name": "Wimborne", 
      "urls": {
        "self": "https://www.givefood.org.uk/api/2/foodbank/wimborne/", 
        "html": "https://www.givefood.org.uk/needs/at/wimborne/"
      }, 
      "slug": "wimborne"
    }, 
    "self": "https://www.givefood.org.uk/api/2/needs/96dcaf64/"
  }, 
  {
    "found": "2020-12-18T21:07:36.119Z", 
    "needs": "Custard Powder\r\nTinned Fruit\r\nSponge Puddings\r\nJam\r\nTinned Potatoes", 
    "id": "c630ee84", 
    "foodbank": {
      "name": "Brecon", 
      "urls": {
        "self": "https://www.givefood.org.uk/api/2/foodbank/brecon/", 
        "html": "https://www.givefood.org.uk/needs/at/brecon/"
      }, 
      "slug": "brecon"
    }, 
    "self": "https://www.givefood.org.uk/api/2/needs/c630ee84/"
  }, 
  {
    "found": "2020-12-18T18:37:41.992Z", 
    "needs": "Instant Mashed Potato\r\nUHT Fruit Juice\r\nJam\r\nTinned Fruit\r\nTinned Potatoes And Carrots\r\nSnacks; Like Chocolate And Crisps\r\nShampoo, Deodorant And Shower Gel\r\nWashing Powder And Liquids\r\nToothbrushes\r\nToilet Roll", 
    "id": "d008a149", 
    "foodbank": {
      "name": "Chepstow", 
      "urls": {
        "self": "https://www.givefood.org.uk/api/2/foodbank/chepstow/", 
        "html": "https://www.givefood.org.uk/needs/at/chepstow/"
      }, 
      "slug": "chepstow"
    }, 
    "self": "https://www.givefood.org.uk/api/2/needs/d008a149/"
  }, 
  {
    "found": "2020-12-18T18:29:36.285Z", 
    "needs": "Fray Bentos Meals (Beef Or Chicken)\r\nTinned Fish\r\nUHT Milk (Green Or Blue)", 
    "id": "e4722218", 
    "foodbank": {
      "name": "Loughborough Area", 
      "urls": {
        "self": "https://www.givefood.org.uk/api/2/foodbank/loughborough-area/", 
        "html": "https://www.givefood.org.uk/needs/at/loughborough-area/"
      }, 
      "slug": "loughborough-area"
    }, 
    "self": "https://www.givefood.org.uk/api/2/needs/e4722218/"
  }, 
  {
    "found": "2020-12-18T17:22:18.363Z", 
    "needs": "Chocolate Bars\r\nTinned Fruit\r\nChristmas \r\nMashed Potato\r\nSpam\r\nTinned Salmon\r\nTinned Pork\r\nTinned Ham\r\nTinned Mixed Vegetables", 
    "id": "de3b6c8d", 
    "foodbank": {
      "name": "Woking", 
      "urls": {
        "self": "https://www.givefood.org.uk/api/2/foodbank/woking/", 
        "html": "https://www.givefood.org.uk/needs/at/woking/"
      }, 
      "slug": "woking"
    }, 
    "self": "https://www.givefood.org.uk/api/2/needs/de3b6c8d/"
  }, 
  {
    "found": "2020-12-18T16:34:32.107Z", 
    "needs": "Sponge Puddings\r\nCustard\r\nTinned Potatoes", 
    "id": "dbff2424", 
    "foodbank": {
      "name": "Rugby", 
      "urls": {
        "self": "https://www.givefood.org.uk/api/2/foodbank/rugby/", 
        "html": "https://www.givefood.org.uk/needs/at/rugby/"
      }, 
      "slug": "rugby"
    }, 
    "self": "https://www.givefood.org.uk/api/2/needs/dbff2424/"
  }, 
  {
    "found": "2020-12-18T16:10:25.700Z", 
    "needs": "Pringles\r\nSavoury Biscuits 150g\r\nChocolate Finger Biscuits\r\nChristmas Chocolate Biscuits, Any!\r\nChocolate Sweet Selection Boxes 250-350g\r\nAngel Delight Packets\r\nBags For Life", 
    "id": "5267d52a", 
    "foodbank": {
      "name": "Farnborough", 
      "urls": {
        "self": "https://www.givefood.org.uk/api/2/foodbank/farnborough/", 
        "html": "https://www.givefood.org.uk/needs/at/farnborough/"
      }, 
      "slug": "farnborough"
    }, 
    "self": "https://www.givefood.org.uk/api/2/needs/5267d52a/"
  }, 
  {
    "found": "2020-12-18T14:52:47.390Z", 
    "needs": "Tinned Sponge Puddings\r\nCarton Juice\r\nFrey Bentos Meat Pies\r\nFestive Treats\r\nShampoo & Conditioner\r\nLadies & Mens Deodorant\r\nWashing Capsules\r\nChildrens Toothpaste\r\nChildrens Toothbrushes\r\nBody Wash\r\nAdult Toothbrushes\r\nWashing Up Sponges", 
    "id": "8ade5e4a", 
    "foodbank": {
      "name": "Crowthorne", 
      "urls": {
        "self": "https://www.givefood.org.uk/api/2/foodbank/crowthorne/", 
        "html": "https://www.givefood.org.uk/needs/at/crowthorne/"
      }, 
      "slug": "crowthorne"
    }, 
    "self": "https://www.givefood.org.uk/api/2/needs/8ade5e4a/"
  }, 
  {
    "found": "2020-12-18T14:10:17.654Z", 
    "needs": "Nothing", 
    "id": "b7bafa75", 
    "foodbank": {
      "name": "St Helens", 
      "urls": {
        "self": "https://www.givefood.org.uk/api/2/foodbank/st-helens/", 
        "html": "https://www.givefood.org.uk/needs/at/st-helens/"
      }, 
      "slug": "st-helens"
    }, 
    "self": "https://www.givefood.org.uk/api/2/needs/b7bafa75/"
  }, 
  {
    "found": "2020-12-18T14:00:56.409Z", 
    "needs": "Chocolate\r\nSponge Puddings\r\nInstant Mash\r\nRice Pudding\r\nCustard\r\nUHT Juice\r\nTinned Fruit\r\nBiscuits", 
    "id": "0a610025", 
    "foodbank": {
      "name": "Bath", 
      "urls": {
        "self": "https://www.givefood.org.uk/api/2/foodbank/bath/", 
        "html": "https://www.givefood.org.uk/needs/at/bath/"
      }, 
      "slug": "bath"
    }, 
    "self": "https://www.givefood.org.uk/api/2/needs/0a610025/"
  }, 
  {
    "found": "2020-12-18T13:22:27.306Z", 
    "needs": "Tinned Meat\r\nTinned Carrots\r\nJam\r\nCustard\r\nRice Puddings\r\nTinned Fruit\r\nMashed Potato\r\nLong Life Fruit Juice\r\nTinned Potatoes\r\nSoap\r\nToothpaste", 
    "id": "44e90106", 
    "foodbank": {
      "name": "Redditch", 
      "urls": {
        "self": "https://www.givefood.org.uk/api/2/foodbank/redditch/", 
        "html": "https://www.givefood.org.uk/needs/at/redditch/"
      }, 
      "slug": "redditch"
    }, 
    "self": "https://www.givefood.org.uk/api/2/needs/44e90106/"
  }, 
  {
    "found": "2020-12-18T13:06:45.878Z", 
    "needs": "Fruit Juice (Long-life Cartons)\r\nKetchup/sauces\r\nChocolate Bars\r\nSponge Puddings\r\nTinned Potatoes\r\nPackets Of Potato Mash", 
    "id": "8e3b8d0b", 
    "foodbank": {
      "name": "Gillingham", 
      "urls": {
        "self": "https://www.givefood.org.uk/api/2/foodbank/gillingham/", 
        "html": "https://www.givefood.org.uk/needs/at/gillingham/"
      }, 
      "slug": "gillingham"
    }, 
    "self": "https://www.givefood.org.uk/api/2/needs/8e3b8d0b/"
  }, 
  {
    "found": "2020-12-18T12:58:32.770Z", 
    "needs": "Long-life Milk\r\nSponge Puddings\r\nTinned Custard\r\nRice Pudding\r\nCleaning Products\r\nLaundry Powder Or Liquid\r\nSugar\r\nFruit Juice (Carton)\r\nSoup\r\nPasta Sauces\r\nTinned Tomatoes\r\nCereals\r\nRice Pudding (Tinned)\r\nTea Bags / Instant Coffee\r\nInstant Mashed Potato\r\nRice\r\nPasta\r\nTinned Meat\r\nTinned Fish\r\nTinned Fruit\r\nJam\r\nBiscuits Or Snack Bar\r\nNappies\r\nShower Gel\r\nShampoo\r\nDeodorant\r\nWashing Up Liquid", 
    "id": "315c5875", 
    "foodbank": {
      "name": "Ribble Valley", 
      "urls": {
        "self": "https://www.givefood.org.uk/api/2/foodbank/ribble-valley/", 
        "html": "https://www.givefood.org.uk/needs/at/ribble-valley/"
      }, 
      "slug": "ribble-valley"
    }, 
    "self": "https://www.givefood.org.uk/api/2/needs/315c5875/"
  }, 
  {
    "found": "2020-12-18T12:34:00.213Z", 
    "needs": "Tinned Corned Beef, Ham & Luncheon Meat.\r\nTinned Curry\r\nTinned Meatballs\r\nTinned Pies\r\nTinned Tuna\r\nTinned Sardines\r\nTinned Pilchards\r\nTinned Peas\r\nTinned Carrots\r\nTinned Sweetcorn\r\nTinned Potatoes\r\nTinned Tomatoes,chopped And Plum\r\nBaked Beans\r\nTinned Spaghetti\r\nPackets Of Instant Mashed Potato\r\nTinned & Packet Soup, All Varieties Welcomed.\r\nTinned Fruit, All Varieties Welcomed.\r\nTinned Or Packet Custard,custard Powder\r\nTinned Rice Pudding\r\nSteamed Puddings\r\nPasta,all Types 500g And 1kg\r\nRice, 500gm And 1kg\r\nCooking Sauces.tins,jars Or Packets\r\nJams And Marmalade\r\nBoxed Cereal\r\nBiscuits, Sweet And Savoury\r\nTea Bags 80s And 160s\r\nJars Of Instant Coffee And Chocolate Drink.\r\nLong Life Semi & Whole Milk Cartons, Both 500ml & 1lt Packs\r\nFruit Squash\r\nSoap Toothpaste Toilet Rolls Washing Up Liquid And Laundry Detergents", 
    "id": "e7a80aff", 
    "foodbank": {
      "name": "Chard", 
      "urls": {
        "self": "https://www.givefood.org.uk/api/2/foodbank/chard/", 
        "html": "https://www.givefood.org.uk/needs/at/chard/"
      }, 
      "slug": "chard"
    }, 
    "self": "https://www.givefood.org.uk/api/2/needs/e7a80aff/"
  }, 
  {
    "found": "2020-12-17T22:02:07.677Z", 
    "needs": "Tinned Cold Meat - Ham, Corned Beef, Pork\r\nSponge Puddings\r\nMash Potatoes\r\nDeodorants - Male And Female\r\nShaving Gel\r\nWashing Up Liquid\r\nWashing Powder/liquid/capsules", 
    "id": "1e62bd47", 
    "foodbank": {
      "name": "Newcastle (Staffs)", 
      "urls": {
        "self": "https://www.givefood.org.uk/api/2/foodbank/newcastle-staffs/", 
        "html": "https://www.givefood.org.uk/needs/at/newcastle-staffs/"
      }, 
      "slug": "newcastle-staffs"
    }, 
    "self": "https://www.givefood.org.uk/api/2/needs/1e62bd47/"
  }, 
  {
    "found": "2020-12-17T22:01:23.934Z", 
    "needs": "Christmas Cake (Slab/bar)\r\nMince Pies\r\nBox Of Biscuits\r\nBox Of Chocolates\r\nChocolate Bars\r\nSelection Box\r\nChristmas Crackers\r\nCheese Crackers\r\nLonglife Juice\r\nTinned Potato\r\nInstant Potato [Pkts]\r\nTinned Veg [Not Pulses]\r\nTinned Meat [Not Hotdogs]\r\nTinned Fruit\r\nDried Milk\r\nSugar\r\nSmall Coffee\r\nNappies Size 5", 
    "id": "657d3438", 
    "foodbank": {
      "name": "Letchworth", 
      "urls": {
        "self": "https://www.givefood.org.uk/api/2/foodbank/letchworth/", 
        "html": "https://www.givefood.org.uk/needs/at/letchworth/"
      }, 
      "slug": "letchworth"
    }, 
    "self": "https://www.givefood.org.uk/api/2/needs/657d3438/"
  }, 
  {
    "found": "2020-12-17T21:30:06.306Z", 
    "needs": "Instant Coffee - Small Jars / Tins\r\nMeat Pies / Tinned Hot Dogs\r\nTinned Meatballs, Mince, Etc\r\nTinned Fruit\r\nTinned Vegetables\r\nInstant Packets Soup/noodles Etc\r\nGluten Free Food (But Not Pasta!)\r\nTinned Vegan/vegetarian Meals", 
    "id": "32ea1cc6", 
    "foodbank": {
      "name": "East Elmbridge", 
      "urls": {
        "self": "https://www.givefood.org.uk/api/2/foodbank/east-elmbridge/", 
        "html": "https://www.givefood.org.uk/needs/at/east-elmbridge/"
      }, 
      "slug": "east-elmbridge"
    }, 
    "self": "https://www.givefood.org.uk/api/2/needs/32ea1cc6/"
  }, 
  {
    "found": "2020-12-17T21:18:47.507Z", 
    "needs": "Long Life UHT Milk\r\nMeat Pies\r\nTinned Hot Dog Sausages\r\nDog Food", 
    "id": "77e34613", 
    "foodbank": {
      "name": "Witney & West Oxfordshire", 
      "urls": {
        "self": "https://www.givefood.org.uk/api/2/foodbank/witney-west-oxfordshire/", 
        "html": "https://www.givefood.org.uk/needs/at/witney-west-oxfordshire/"
      }, 
      "slug": "witney-west-oxfordshire"
    }, 
    "self": "https://www.givefood.org.uk/api/2/needs/77e34613/"
  }, 
  {
    "found": "2020-12-17T19:04:52.870Z", 
    "needs": "Tinned Potatoes Or Instant Mash\r\nCustard\r\nTinned Fish\r\nTinned Meat\r\nTinned Fruit\r\nLong Life Fruit Juice\r\nInstant Coffee\r\nUHT Milk", 
    "id": "0480576c", 
    "foodbank": {
      "name": "Swansea", 
      "urls": {
        "self": "https://www.givefood.org.uk/api/2/foodbank/swansea/", 
        "html": "https://www.givefood.org.uk/needs/at/swansea/"
      }, 
      "slug": "swansea"
    }, 
    "self": "https://www.givefood.org.uk/api/2/needs/0480576c/"
  }, 
  {
    "found": "2020-12-17T18:22:14.091Z", 
    "needs": "Tinned Potatoes\r\nInstant Mash\r\nTinned Carrots\r\nTinned Garden Peas", 
    "id": "b61f1f29", 
    "foodbank": {
      "name": "Truro", 
      "urls": {
        "self": "https://www.givefood.org.uk/api/2/foodbank/truro/", 
        "html": "https://www.givefood.org.uk/needs/at/truro/"
      }, 
      "slug": "truro"
    }, 
    "self": "https://www.givefood.org.uk/api/2/needs/b61f1f29/"
  }, 
  {
    "found": "2020-12-17T17:49:39.077Z", 
    "needs": "Tinned Potatoes\r\nTinned Carrots\r\nTinned Meat, Fish, Fruit, Vegetables, Beans, Soup, Rice Pudding, Custard\r\nTea, Coffee, UHT Milk, Fruit Juice, Fruit Squash\r\nCereals (Medium)\r\nJam, Peanut Butter\r\nPasta (500g)\r\nRice (500g)\r\nInstant Mash\r\nSauces For Rice And Pasta\r\nSugar (500g)\r\nTreats: Biscuits, Chocolate, Sweets Etc\r\nPersonal Hygiene Items - Shower Gel, Shampoo, Deodorant, Toilet Rolls\r\nHousehold Cleaning Items - Washing Powder, Washing Up Liquid, Surface Cleaner", 
    "id": "043c0ec5", 
    "foodbank": {
      "name": "Malvern Hills", 
      "urls": {
        "self": "https://www.givefood.org.uk/api/2/foodbank/malvern-hills/", 
        "html": "https://www.givefood.org.uk/needs/at/malvern-hills/"
      }, 
      "slug": "malvern-hills"
    }, 
    "self": "https://www.givefood.org.uk/api/2/needs/043c0ec5/"
  }, 
  {
    "found": "2020-12-17T17:10:27.227Z", 
    "needs": "Long Life Fruit Juice\r\nSponge Pudding\r\nBar Of Chocolate\r\nToothbrushes", 
    "id": "3e4c0439", 
    "foodbank": {
      "name": "Salisbury", 
      "urls": {
        "self": "https://www.givefood.org.uk/api/2/foodbank/salisbury/", 
        "html": "https://www.givefood.org.uk/needs/at/salisbury/"
      }, 
      "slug": "salisbury"
    }, 
    "self": "https://www.givefood.org.uk/api/2/needs/3e4c0439/"
  }, 
  {
    "found": "2020-12-17T15:42:34.521Z", 
    "needs": "Meat Such As Corned Beef Or Ham\r\nLong Life Milk\r\nTea\r\nCoffee & Sugar\r\nMeat Meals\r\nTinned Tomatoes\r\nPotatoes\r\nCustard & Rice Pudding\r\nToothpaste\r\nSoap\r\nSanitary Pads\r\nNappies Sizes 5  To 6 Plus And Pet Food For Dogs And Cats\r\nGifts For All Ages\r\nEspecially Mums And Teenagers As They Are In Very Short Supply\r\nMince Pies\r\nSelection Boxes\r\nSponge Pudding Or Christmas Pudding\r\nWrapping Paper And Tape", 
    "id": "6eb438a0", 
    "foodbank": {
      "name": "The Raft Foundation", 
      "urls": {
        "self": "https://www.givefood.org.uk/api/2/foodbank/the-raft-foundation/", 
        "html": "https://www.givefood.org.uk/needs/at/the-raft-foundation/"
      }, 
      "slug": "the-raft-foundation"
    }, 
    "self": "https://www.givefood.org.uk/api/2/needs/6eb438a0/"
  }, 
  {
    "found": "2020-12-17T14:47:17.581Z", 
    "needs": "Nothing", 
    "id": "f6825bcb", 
    "foodbank": {
      "name": "Atherton & Leigh", 
      "urls": {
        "self": "https://www.givefood.org.uk/api/2/foodbank/atherton-leigh/", 
        "html": "https://www.givefood.org.uk/needs/at/atherton-leigh/"
      }, 
      "slug": "atherton-leigh"
    }, 
    "self": "https://www.givefood.org.uk/api/2/needs/f6825bcb/"
  }, 
  {
    "found": "2020-12-17T14:40:51.694Z", 
    "needs": "Tinned Vegetables (Carrots, Peas, Sweetcorn)\r\n500g Bags Of Dried Pasta\r\nTinned Meat Meals\r\nBottles Of Squash\r\nSingle Adult Toothbrushes\r\nTwin-packed Sponge Puddings\r\nSnack Bars\r\nUHT Milk (Full-fat)\r\nSugar", 
    "id": "9349167f", 
    "foodbank": {
      "name": "Dorking Area", 
      "urls": {
        "self": "https://www.givefood.org.uk/api/2/foodbank/dorking-area/", 
        "html": "https://www.givefood.org.uk/needs/at/dorking-area/"
      }, 
      "slug": "dorking-area"
    }, 
    "self": "https://www.givefood.org.uk/api/2/needs/9349167f/"
  }, 
  {
    "found": "2020-12-17T13:36:44.116Z", 
    "needs": "Tinned Vegetables (Peas, Sweetcorn, Carrots Etc.)\r\nPorridge\r\nSpreads (Jam, Marmalade, Honey, Peanut Butter Etc.)\r\nDesserts (Sponge Puddings, Jelly, Angel Delight Etc)\r\nFeminine Hygiene (Towels & Tampons)\r\nWashing Up Liquid\r\nCoffee\r\nDrinking Chocolate\r\nInstant Noodles / Pasta Sauces\r\nLoo Rolls\r\nDeodorants (Men's And Women's)", 
    "id": "710aae64", 
    "foodbank": {
      "name": "Eastleigh Basics Bank", 
      "urls": {
        "self": "https://www.givefood.org.uk/api/2/foodbank/eastleigh-basics-bank/", 
        "html": "https://www.givefood.org.uk/needs/at/eastleigh-basics-bank/"
      }, 
      "slug": "eastleigh-basics-bank"
    }, 
    "self": "https://www.givefood.org.uk/api/2/needs/710aae64/"
  }, 
  {
    "found": "2020-12-17T13:14:41.429Z", 
    "needs": "Tinned Meals\r\nTinned Dessert\r\nTinned Fruit", 
    "id": "fe6afe10", 
    "foodbank": {
      "name": "Lincoln", 
      "urls": {
        "self": "https://www.givefood.org.uk/api/2/foodbank/lincoln/", 
        "html": "https://www.givefood.org.uk/needs/at/lincoln/"
      }, 
      "slug": "lincoln"
    }, 
    "self": "https://www.givefood.org.uk/api/2/needs/fe6afe10/"
  }, 
  {
    "found": "2020-12-17T13:02:39.508Z", 
    "needs": "Cereal\r\nUHT Milk\r\nCustard - Ready Made\r\nFruit Juice\r\nPacket Mash Potato\r\nPot Noodles\r\nNappies Size 5 And 6\r\nHousehold Cleaning Items\r\nKitchen Towels", 
    "id": "e16f8aac", 
    "foodbank": {
      "name": "Keynsham", 
      "urls": {
        "self": "https://www.givefood.org.uk/api/2/foodbank/keynsham/", 
        "html": "https://www.givefood.org.uk/needs/at/keynsham/"
      }, 
      "slug": "keynsham"
    }, 
    "self": "https://www.givefood.org.uk/api/2/needs/e16f8aac/"
  }, 
  {
    "found": "2020-12-17T09:51:05.023Z", 
    "needs": "Tinned Potatoes\r\nTinned Spaghetti/hoops/ravioli\r\nCustard\r\nInstant Mash\r\nCrisps/savoury Snacks/chocolate Bars\r\nTinned Fruit\r\nShampoo\r\nDeodorants", 
    "id": "8a8ad950", 
    "foodbank": {
      "name": "Weston-super-Mare", 
      "urls": {
        "self": "https://www.givefood.org.uk/api/2/foodbank/weston-super-mare/", 
        "html": "https://www.givefood.org.uk/needs/at/weston-super-mare/"
      }, 
      "slug": "weston-super-mare"
    }, 
    "self": "https://www.givefood.org.uk/api/2/needs/8a8ad950/"
  }, 
  {
    "found": "2020-12-17T09:27:07.066Z", 
    "needs": "Strong Supermarket  Bags Or Bags For Life\r\nTins Of Meat Casserole (Ideally 2/3 Tins Same Thing For Large Families)\r\nTinned Corn Beef, Ham Etc\r\nPasta Sauce\r\nTinned Potatoes\r\nTinned Carrots & Peas\r\nTinned Fruit\r\nTinned Custard", 
    "id": "c4d82a0b", 
    "foodbank": {
      "name": "Loveworks", 
      "urls": {
        "self": "https://www.givefood.org.uk/api/2/foodbank/loveworks/", 
        "html": "https://www.givefood.org.uk/needs/at/loveworks/"
      }, 
      "slug": "loveworks"
    }, 
    "self": "https://www.givefood.org.uk/api/2/needs/c4d82a0b/"
  }, 
  {
    "found": "2020-12-17T05:27:09.359Z", 
    "needs": "Fruit Juice (longlife)\r\nTinned Chicken (small)\r\nSponge Pudding (longlife)\r\nTinned Vegetables\r\nRice Pudding\r\nDeodorant (male/female/universal)\r\nAnti-Bac Spray Cleaners", 
    "id": "712e7bb3", 
    "foodbank": {
      "name": "Bedford", 
      "urls": {
        "self": "https://www.givefood.org.uk/api/2/foodbank/bedford/", 
        "html": "https://www.givefood.org.uk/needs/at/bedford/"
      }, 
      "slug": "bedford"
    }, 
    "self": "https://www.givefood.org.uk/api/2/needs/712e7bb3/"
  }, 
  {
    "found": "2020-12-17T00:55:00.254Z", 
    "needs": "Fruit Juice (Long Life)\r\nSponge Puddings\r\nToothbrushes (Kids And Adults)\r\nWashing Up Liquid\r\nLaundry Detergent (Tablets Please)\r\nShampoo And Conditioner\r\nShaving Foam And Razors\r\nDeodorant", 
    "id": "0e77f145", 
    "foodbank": {
      "name": "Abergavenny", 
      "urls": {
        "self": "https://www.givefood.org.uk/api/2/foodbank/abergavenny/", 
        "html": "https://www.givefood.org.uk/needs/at/abergavenny/"
      }, 
      "slug": "abergavenny"
    }, 
    "self": "https://www.givefood.org.uk/api/2/needs/0e77f145/"
  }, 
  {
    "found": "2020-12-16T20:41:07.221Z", 
    "needs": "Long Life Juice\r\nTinned Fruit\r\nPasta\r\nTinned Tomatoes\r\nTinned Soup\r\nTinned Potatoes\r\nLadies Toiletries", 
    "id": "1e3f9ca5", 
    "foodbank": {
      "name": "Cheadle and District", 
      "urls": {
        "self": "https://www.givefood.org.uk/api/2/foodbank/cheadle-and-district/", 
        "html": "https://www.givefood.org.uk/needs/at/cheadle-and-district/"
      }, 
      "slug": "cheadle-and-district"
    }, 
    "self": "https://www.givefood.org.uk/api/2/needs/1e3f9ca5/"
  }, 
  {
    "found": "2020-12-16T19:37:25.655Z", 
    "needs": "Tinned Ham For Christmas Packs\r\nLong Life Fruit Juice\r\nSavoury Snacks For Christmas Packs\r\nSponge Puddings\r\nTinned And Instant Mashed Potatoes\r\nSmall Christmas Cakes", 
    "id": "c7fa9ba2", 
    "foodbank": {
      "name": "Leeds North & West", 
      "urls": {
        "self": "https://www.givefood.org.uk/api/2/foodbank/leeds-north-west/", 
        "html": "https://www.givefood.org.uk/needs/at/leeds-north-west/"
      }, 
      "slug": "leeds-north-west"
    }, 
    "self": "https://www.givefood.org.uk/api/2/needs/c7fa9ba2/"
  }, 
  {
    "found": "2020-12-16T19:17:18.582Z", 
    "needs": "Single Toothbrushes\r\nLaundry Fabric Conditioner", 
    "id": "0e4afe8f", 
    "foodbank": {
      "name": "Stretford", 
      "urls": {
        "self": "https://www.givefood.org.uk/api/2/foodbank/stretford/", 
        "html": "https://www.givefood.org.uk/needs/at/stretford/"
      }, 
      "slug": "stretford"
    }, 
    "self": "https://www.givefood.org.uk/api/2/needs/0e4afe8f/"
  }, 
  {
    "found": "2020-12-16T18:16:14.197Z", 
    "needs": "Jam\r\nTinned Peas\r\nTinned Carrots\r\nTinned Vegetables\r\nTinned Spaghetti\r\nTinned Tomatoes\r\nSavoury Biscuits\r\nSweet Biscuits\r\nShampoo\r\nShower Gel\r\nSoap\r\nToothpaste", 
    "id": "15b3f480", 
    "foodbank": {
      "name": "Alnwick District", 
      "urls": {
        "self": "https://www.givefood.org.uk/api/2/foodbank/alnwick-district/", 
        "html": "https://www.givefood.org.uk/needs/at/alnwick-district/"
      }, 
      "slug": "alnwick-district"
    }, 
    "self": "https://www.givefood.org.uk/api/2/needs/15b3f480/"
  }, 
  {
    "found": "2020-12-16T18:13:16.372Z", 
    "needs": "Dry And Tinned Goods", 
    "id": "4d496ee5", 
    "foodbank": {
      "name": "Hearts and Hands Stafford", 
      "urls": {
        "self": "https://www.givefood.org.uk/api/2/foodbank/hearts-and-hands-stafford/", 
        "html": "https://www.givefood.org.uk/needs/at/hearts-and-hands-stafford/"
      }, 
      "slug": "hearts-and-hands-stafford"
    }, 
    "self": "https://www.givefood.org.uk/api/2/needs/4d496ee5/"
  }, 
  {
    "found": "2020-12-16T17:39:15.606Z", 
    "needs": "Savoury Biscuits 150g\r\nChocolate Finger Biscuits\r\nChristmas Chocolate Biscuits, Any!\r\nChocolate Sweet Selection Boxes 250-350g\r\nAngel Delight Packets\r\nBags For Life", 
    "id": "2400c55e", 
    "foodbank": {
      "name": "Farnborough", 
      "urls": {
        "self": "https://www.givefood.org.uk/api/2/foodbank/farnborough/", 
        "html": "https://www.givefood.org.uk/needs/at/farnborough/"
      }, 
      "slug": "farnborough"
    }, 
    "self": "https://www.givefood.org.uk/api/2/needs/2400c55e/"
  }, 
  {
    "found": "2020-12-16T16:35:20.034Z", 
    "needs": "Chocolate Bars\r\nTinned Fruit\r\nChristmas \r\nTinned Mixed Vegetables", 
    "id": "1f9288ad", 
    "foodbank": {
      "name": "Woking", 
      "urls": {
        "self": "https://www.givefood.org.uk/api/2/foodbank/woking/", 
        "html": "https://www.givefood.org.uk/needs/at/woking/"
      }, 
      "slug": "woking"
    }, 
    "self": "https://www.givefood.org.uk/api/2/needs/1f9288ad/"
  }, 
  {
    "found": "2020-12-16T15:34:00.507Z", 
    "needs": "Tinned Ham\r\nTinned Potatoes\r\nTinned Custard\r\nCup-a-soup/pot Noodles\r\nSmall Jars Of Coffee\r\nJam Or Spreads\r\nShower Gel\r\nToothbrushes (Single) & Toothpaste\r\nDeodorant\r\nShampoo\r\nSanitary Towels & Tampons", 
    "id": "c123000f", 
    "foodbank": {
      "name": "Gloucester", 
      "urls": {
        "self": "https://www.givefood.org.uk/api/2/foodbank/gloucester/", 
        "html": "https://www.givefood.org.uk/needs/at/gloucester/"
      }, 
      "slug": "gloucester"
    }, 
    "self": "https://www.givefood.org.uk/api/2/needs/c123000f/"
  }, 
  {
    "found": "2020-12-16T15:13:26.519Z", 
    "needs": "Nappies 4+\r\nToilet Roll\r\nRazors\r\nDeodorant\r\nWashing Detergent\r\nFabric Conditioner\r\nWashing-up Liquid\r\nFruit Juice / Squash", 
    "id": "7f2be98e", 
    "foodbank": {
      "name": "Corby", 
      "urls": {
        "self": "https://www.givefood.org.uk/api/2/foodbank/corby/", 
        "html": "https://www.givefood.org.uk/needs/at/corby/"
      }, 
      "slug": "corby"
    }, 
    "self": "https://www.givefood.org.uk/api/2/needs/7f2be98e/"
  }, 
  {
    "found": "2020-12-16T13:30:38.373Z", 
    "needs": "Tinned Fish\r\nTinned Tomatoes\r\nToothpaste\r\nDeodorant\r\n Our Food \r\nRice Pudding (Tinned)\r\nFruit Juice (Carton)\r\nBiscuits (Sweet And Savoury)\r\nTomatoes (Tinned)\r\nPasta & Pasta Sauces\r\nMilk (UHT Or Powdered)\r\nFruit (Tinned)\r\nCereals\r\nBeans\r\nTea Bags\r\nInstant Coffee\r\nTinned Meat\r\nTinned Fish\r\nSweet Treats\r\nShower Gel\r\nShampoo\r\nToothbrushes\r\nToothpaste\r\nDeodorant\r\nSanitary Towels\r\nToilet Rolls", 
    "id": "0c1705d5", 
    "foodbank": {
      "name": "Portsmouth", 
      "urls": {
        "self": "https://www.givefood.org.uk/api/2/foodbank/portsmouth/", 
        "html": "https://www.givefood.org.uk/needs/at/portsmouth/"
      }, 
      "slug": "portsmouth"
    }, 
    "self": "https://www.givefood.org.uk/api/2/needs/0c1705d5/"
  }, 
  {
    "found": "2020-12-16T13:03:06.984Z", 
    "needs": "Tinned Fruit\r\nTinned Tomatoes\r\nSugar\r\nFruit Juice (Long Life)\r\nTinned Fish\r\nTinned Vegetables\r\nInstant Coffee\r\nInstant Mash\r\nJars Of Pasta/curry Sauce\r\nJam\r\nTinned Rice Pudding/custard\r\nBiscuits\r\nTinned Potatoes\r\nPackets Of Savoury Rice\r\nToiletries", 
    "id": "bea8f426", 
    "foodbank": {
      "name": "St Helens", 
      "urls": {
        "self": "https://www.givefood.org.uk/api/2/foodbank/st-helens/", 
        "html": "https://www.givefood.org.uk/needs/at/st-helens/"
      }, 
      "slug": "st-helens"
    }, 
    "self": "https://www.givefood.org.uk/api/2/needs/bea8f426/"
  }, 
  {
    "found": "2020-12-16T12:56:12.542Z", 
    "needs": "Tea\r\nShampoo\r\nToothpaste/toothbrushes\r\nMeat Soup Eg Chicken\r\nFemale Deodorant\r\nWashing Powder (Small Boxes)", 
    "id": "0227b23b", 
    "foodbank": {
      "name": "Chorlton & Didsbury", 
      "urls": {
        "self": "https://www.givefood.org.uk/api/2/foodbank/chorlton-didsbury/", 
        "html": "https://www.givefood.org.uk/needs/at/chorlton-didsbury/"
      }, 
      "slug": "chorlton-didsbury"
    }, 
    "self": "https://www.givefood.org.uk/api/2/needs/0227b23b/"
  }, 
  {
    "found": "2020-12-16T12:41:59.930Z", 
    "needs": "Tinned Meat\r\nLong Life Juice\r\nTinned Fish\r\nRice\r\nCereal\r\nTinned Fruit\r\nRice Pudding\r\nWashing Up Liquid\r\nWashing Up Powder\r\nToiletries ( Shaving Foam, Shampoo, Conditioner, Toothpaste, Toilet Roll)\r\nMen's Razors", 
    "id": "1315ca1e", 
    "foodbank": {
      "name": "Aberdeen North", 
      "urls": {
        "self": "https://www.givefood.org.uk/api/2/foodbank/aberdeen-north/", 
        "html": "https://www.givefood.org.uk/needs/at/aberdeen-north/"
      }, 
      "slug": "aberdeen-north"
    }, 
    "self": "https://www.givefood.org.uk/api/2/needs/1315ca1e/"
  }, 
  {
    "found": "2020-12-16T11:58:01.081Z", 
    "needs": "Juice/dilute\r\nCustard\r\nTinned Fish\r\nTinned Fruit\r\nTinned Meat/pies", 
    "id": "e4056291", 
    "foodbank": {
      "name": "Barnsley", 
      "urls": {
        "self": "https://www.givefood.org.uk/api/2/foodbank/barnsley/", 
        "html": "https://www.givefood.org.uk/needs/at/barnsley/"
      }, 
      "slug": "barnsley"
    }, 
    "self": "https://www.givefood.org.uk/api/2/needs/e4056291/"
  }, 
  {
    "found": "2020-12-16T11:31:08.093Z", 
    "needs": "Long-life Milk\r\nLong-life Sponge Pudding\r\nInstant Mash/tinned Potatoes\r\nRice Pudding\r\nLong-life Juice\r\nJars Of Instant Coffee\r\nTinned Meat\r\nTeabags (40s/80s)\r\nChocolate Treats For Children\r\nTinned Fruit", 
    "id": "ccf529a3", 
    "foodbank": {
      "name": "Cirencester", 
      "urls": {
        "self": "https://www.givefood.org.uk/api/2/foodbank/cirencester/", 
        "html": "https://www.givefood.org.uk/needs/at/cirencester/"
      }, 
      "slug": "cirencester"
    }, 
    "self": "https://www.givefood.org.uk/api/2/needs/ccf529a3/"
  }, 
  {
    "found": "2020-12-16T09:40:19.398Z", 
    "needs": "Tinned Rice Pudding\r\nTinned Fruit\r\nMash\r\nChocolates For Christmas\r\nSmall Tea Bags 40's\r\nFruit Juice\r\nCereal\r\nTinned Soup\r\nTinned Tomato\r\nJar Pasta Sauce\r\nTinned Vegetables\r\nTinned Meat\r\nTinned Fish\r\nRice Pudding\r\nTinned Fruit\r\nTinned Sponge Pudding\r\nBiscuits\r\nDried Pasta/rice\r\nTea Bags\r\nUHT Fruit Juice\r\nUHT Milk\r\nSavoury Treats\r\nSweet Treats / Chocolate Etc", 
    "id": "150a2606", 
    "foodbank": {
      "name": "Stoke-on-Trent", 
      "urls": {
        "self": "https://www.givefood.org.uk/api/2/foodbank/stoke-on-trent/", 
        "html": "https://www.givefood.org.uk/needs/at/stoke-on-trent/"
      }, 
      "slug": "stoke-on-trent"
    }, 
    "self": "https://www.givefood.org.uk/api/2/needs/150a2606/"
  }, 
  {
    "found": "2020-12-16T00:27:21.357Z", 
    "needs": "Sponge Puddings\r\nJam\r\nTinned Rice Pudding Or Custard\r\nTinned Fish\r\nDeodorants", 
    "id": "715373ce", 
    "foodbank": {
      "name": "South Liverpool", 
      "urls": {
        "self": "https://www.givefood.org.uk/api/2/foodbank/south-liverpool/", 
        "html": "https://www.givefood.org.uk/needs/at/south-liverpool/"
      }, 
      "slug": "south-liverpool"
    }, 
    "self": "https://www.givefood.org.uk/api/2/needs/715373ce/"
  }, 
  {
    "found": "2020-12-16T00:21:53.459Z", 
    "needs": "Tinned Fruit (400gms)\r\nTinned Stewed Beef (400gms)\r\nTinned Curry (400gms)\r\nTinned Pies (Freys Bentos)\r\nPulses (Kidney Beans, Chick Peas) (400gms)\r\nTinned Fish (Makrel, Tuna)\r\nTinned Veg (Sweetcorn, Peas, Carrots)", 
    "id": "77829a5d", 
    "foodbank": {
      "name": "Newquay", 
      "urls": {
        "self": "https://www.givefood.org.uk/api/2/foodbank/newquay/", 
        "html": "https://www.givefood.org.uk/needs/at/newquay/"
      }, 
      "slug": "newquay"
    }, 
    "self": "https://www.givefood.org.uk/api/2/needs/77829a5d/"
  }, 
  {
    "found": "2020-12-16T00:02:54.897Z", 
    "needs": "Tinned Meatballs\r\nTinned Hotdogs\r\nTinned Meat Pies\r\nTinned Fruit\r\nTinned Peas\r\nTinned Sweetcorn\r\nTinned Carrots\r\nTinned Custard\r\nJam, Peanut Butter, Honey\r\nCooking Sauces\r\nTinned Potatoes\r\nInstant Mashed Potato\r\nTinned Rice Pudding\r\nInstant Coffee", 
    "id": "cf2ff9e9", 
    "foodbank": {
      "name": "Borehamwood", 
      "urls": {
        "self": "https://www.givefood.org.uk/api/2/foodbank/borehamwood/", 
        "html": "https://www.givefood.org.uk/needs/at/borehamwood/"
      }, 
      "slug": "borehamwood"
    }, 
    "self": "https://www.givefood.org.uk/api/2/needs/cf2ff9e9/"
  }, 
  {
    "found": "2020-12-15T23:23:34.158Z", 
    "needs": "Fruit Juice (Long Life)\r\nSponge Puddings\r\nToothbrushes (Kids And Adults)\r\nWashing Up Liquid\r\nLaundry Detergent (Tablets Please)\r\nSponge Puddings\r\nDeodorant", 
    "id": "f193a42e", 
    "foodbank": {
      "name": "Abergavenny", 
      "urls": {
        "self": "https://www.givefood.org.uk/api/2/foodbank/abergavenny/", 
        "html": "https://www.givefood.org.uk/needs/at/abergavenny/"
      }, 
      "slug": "abergavenny"
    }, 
    "self": "https://www.givefood.org.uk/api/2/needs/f193a42e/"
  }, 
  {
    "found": "2020-12-15T23:01:41.323Z", 
    "needs": "Sponge Puddings\r\nDeodorant\r\nMilk Powder\r\nSavoury Biscuits\r\nChocolate And Sweets\r\nFruit Juice\r\nTinned Fruit\r\nInstant Custard\r\nPickle\r\nTinned Ham\r\nChristmas Puddings\r\nGifts For Women And Men\r\nGifts For Boys Aged 5 To 12", 
    "id": "b584f81e", 
    "foodbank": {
      "name": "Saltash", 
      "urls": {
        "self": "https://www.givefood.org.uk/api/2/foodbank/saltash/", 
        "html": "https://www.givefood.org.uk/needs/at/saltash/"
      }, 
      "slug": "saltash"
    }, 
    "self": "https://www.givefood.org.uk/api/2/needs/b584f81e/"
  }, 
  {
    "found": "2020-12-15T22:13:29.988Z", 
    "needs": "Washing Detergent\r\nShaving Foam/gel\r\nTinned Meat\r\nCustard\r\nRice Pudding\r\nTinned Fruit\r\nSponge Puddings\r\nJam\r\nSmall Jars Of Coffee\r\nShampoo & Conditioner\r\nDeodorant\r\nToilet Rolls\r\nTinned Potatoes\r\nTinned Spaghetti\r\nChutney\r\nStuffing\r\nChristmas Cake\r\nChristmassy Cake Items/sweet Snacks\r\n'Soft Drinks' (Not Chilled)", 
    "id": "2484f2c1", 
    "foodbank": {
      "name": "Brecon", 
      "urls": {
        "self": "https://www.givefood.org.uk/api/2/foodbank/brecon/", 
        "html": "https://www.givefood.org.uk/needs/at/brecon/"
      }, 
      "slug": "brecon"
    }, 
    "self": "https://www.givefood.org.uk/api/2/needs/2484f2c1/"
  }, 
  {
    "found": "2020-12-15T19:42:13.665Z", 
    "needs": "Dried Rice 500g / 1kg Bags - Urgent\r\nTinned Carrots - Urgent\r\nSmall & Medium Jars Of Instant Coffee - Urgent\r\nTinned Sweetcorn\r\nTinned Potatoes\r\nTinned Meat\r\nTinned Fish\r\nLong - Life Milk - Green Cartons\r\nJam Or Marmalade", 
    "id": "fe3f91b7", 
    "foodbank": {
      "name": "East Grinstead", 
      "urls": {
        "self": "https://www.givefood.org.uk/api/2/foodbank/east-grinstead/", 
        "html": "https://www.givefood.org.uk/needs/at/east-grinstead/"
      }, 
      "slug": "east-grinstead"
    }, 
    "self": "https://www.givefood.org.uk/api/2/needs/fe3f91b7/"
  }, 
  {
    "found": "2020-12-15T18:42:39.164Z", 
    "needs": "Small Jars Of Coffee\r\nPackets Of Mash Potato\r\nTinned Potatoes\r\nTinned Carrots\r\nGravy Granules\r\nTinned Sweetcorn\r\nTinned Custard", 
    "id": "d7aae1e2", 
    "foodbank": {
      "name": "South Gwynedd", 
      "urls": {
        "self": "https://www.givefood.org.uk/api/2/foodbank/south-gwynedd/", 
        "html": "https://www.givefood.org.uk/needs/at/south-gwynedd/"
      }, 
      "slug": "south-gwynedd"
    }, 
    "self": "https://www.givefood.org.uk/api/2/needs/d7aae1e2/"
  }, 
  {
    "found": "2020-12-15T18:11:36.314Z", 
    "needs": "Jars Of Coffee\r\nSponge Puddings", 
    "id": "63cb5d71", 
    "foodbank": {
      "name": "North Cotswold", 
      "urls": {
        "self": "https://www.givefood.org.uk/api/2/foodbank/north-cotswold/", 
        "html": "https://www.givefood.org.uk/needs/at/north-cotswold/"
      }, 
      "slug": "north-cotswold"
    }, 
    "self": "https://www.givefood.org.uk/api/2/needs/63cb5d71/"
  }, 
  {
    "found": "2020-12-15T17:32:10.361Z", 
    "needs": "Tinned Vegetables\r\nTinned Potatoes\r\nTinned Custard\r\nTinned Fruit\r\n4-packs Of Loo Roll\r\nLaundry Tablets\r\nHandsoap\r\nWashing Up Liquid\r\nCan Openers (Not Food But Really Important!)", 
    "id": "856188c5", 
    "foodbank": {
      "name": "Wandsworth", 
      "urls": {
        "self": "https://www.givefood.org.uk/api/2/foodbank/wandsworth/", 
        "html": "https://www.givefood.org.uk/needs/at/wandsworth/"
      }, 
      "slug": "wandsworth"
    }, 
    "self": "https://www.givefood.org.uk/api/2/needs/856188c5/"
  }, 
  {
    "found": "2020-12-15T16:55:29.013Z", 
    "needs": "Long Life Milk\r\nPowdered Milk\r\nLong Life Fruit Juice\r\nPasta Sauces - Especially Tomato-based (I.e. Not Curry Sauces)\r\nSponge Pudding (Tinned / Long Life)\r\nTinned Custard\r\nTomatoes (Tinned)\r\nTinned Veg - Especially Carrots, Sweetcorn And Green Beans Including Ring Pull Please\r\nTinned Potatoes\r\nRice Pudding (Tinned)\r\nTea Bags (40s And 80s)\r\nInstant Coffee\r\nInstant Mash Potato\r\nSnack Bars (E.g. Breakfast Biscuits)\r\nTinned Meat E.g. Ham, Chicken In Sauce, Corned Beef\r\nTinned Fish\r\nTinned Fruit\r\nBiscuits (Sweet)\r\nNappies\r\nJam\r\nPeanut Butter\r\nSweets / Bars Of Chocolate\r\nPet Food (Dog And Cat)\r\nWashing Up Liquid And Sponges\r\nSoap Powder / Washing Gel (Small Quantities)\r\nSanitary Towels / Tampons\r\nToiletries Including Deodorants, Shower Gel, Shampoo, Toilet Rolls, Shaving Gel / Foam And Razors Etc.", 
    "id": "dae38f58", 
    "foodbank": {
      "name": "Norwich", 
      "urls": {
        "self": "https://www.givefood.org.uk/api/2/foodbank/norwich/", 
        "html": "https://www.givefood.org.uk/needs/at/norwich/"
      }, 
      "slug": "norwich"
    }, 
    "self": "https://www.givefood.org.uk/api/2/needs/dae38f58/"
  }, 
  {
    "found": "2020-12-15T16:51:40.272Z", 
    "needs": "Sponge Puddings\r\nTinned Fish\r\nWashing Up Liquid", 
    "id": "cb2fe136", 
    "foodbank": {
      "name": "York", 
      "urls": {
        "self": "https://www.givefood.org.uk/api/2/foodbank/york/", 
        "html": "https://www.givefood.org.uk/needs/at/york/"
      }, 
      "slug": "york"
    }, 
    "self": "https://www.givefood.org.uk/api/2/needs/cb2fe136/"
  }, 
  {
    "found": "2020-12-15T15:33:55.867Z", 
    "needs": "Cleaning Products And Washing Up Liquid\r\nBags For Life\r\nCustard\r\nTinned Fruit\r\nSponge Puddings\r\nMash\r\nHair Conditioner\r\nCoffee\r\nChocolate Bars\r\nTinned Pies", 
    "id": "0a839fe9", 
    "foodbank": {
      "name": "Leek & District", 
      "urls": {
        "self": "https://www.givefood.org.uk/api/2/foodbank/leek-district/", 
        "html": "https://www.givefood.org.uk/needs/at/leek-district/"
      }, 
      "slug": "leek-district"
    }, 
    "self": "https://www.givefood.org.uk/api/2/needs/0a839fe9/"
  }, 
  {
    "found": "2020-12-15T14:56:03.558Z", 
    "needs": "Tinned Potatoes, Carrots, Garden Peas\r\nPeanut Butter\r\nToiletries\r\nToilet Paper\r\nTinned Meats\r\nChocolate\r\nTinned Custard\r\nJam\r\nWash Powder\r\nCleaning (Disinfectant, Washing Up Liquid, Dishcloths Etc)\r\nDog & Cat Food", 
    "id": "13b9c987", 
    "foodbank": {
      "name": "Welshpool and District", 
      "urls": {
        "self": "https://www.givefood.org.uk/api/2/foodbank/welshpool-and-district/", 
        "html": "https://www.givefood.org.uk/needs/at/welshpool-and-district/"
      }, 
      "slug": "welshpool-and-district"
    }, 
    "self": "https://www.givefood.org.uk/api/2/needs/13b9c987/"
  }, 
  {
    "found": "2020-12-15T13:21:57.172Z", 
    "needs": "Bags For Life\r\nCustard\r\nTinned Fruit\r\nSponge Puddings\r\nMash\r\nHair Conditioner\r\nCoffee\r\nChocolate Bars\r\nTinned Pies", 
    "id": "33d39088", 
    "foodbank": {
      "name": "Leek & District", 
      "urls": {
        "self": "https://www.givefood.org.uk/api/2/foodbank/leek-district/", 
        "html": "https://www.givefood.org.uk/needs/at/leek-district/"
      }, 
      "slug": "leek-district"
    }, 
    "self": "https://www.givefood.org.uk/api/2/needs/33d39088/"
  }, 
  {
    "found": "2020-12-15T13:20:16.028Z", 
    "needs": "Instant Mash Potato\r\nSponge Puddings\r\nTea\r\nHot Chocolate\r\nTinned Potatoes", 
    "id": "4359e1b4", 
    "foodbank": {
      "name": "Horsham District", 
      "urls": {
        "self": "https://www.givefood.org.uk/api/2/foodbank/horsham-district/", 
        "html": "https://www.givefood.org.uk/needs/at/horsham-district/"
      }, 
      "slug": "horsham-district"
    }, 
    "self": "https://www.givefood.org.uk/api/2/needs/4359e1b4/"
  }, 
  {
    "found": "2020-12-15T13:14:41.308Z", 
    "needs": "Coffee\r\nJuice & Squash\r\nTinned Meat\r\nTinned Vegetables\r\nTinned Fruit\r\nJams & Spreads\r\nCooking Oil\r\nSauces & Seasonings\r\nSoap (Bars & Handwash)\r\nShampoo\r\nLaundry Powder", 
    "id": "39c77e7d", 
    "foodbank": {
      "name": "Brent", 
      "urls": {
        "self": "https://www.givefood.org.uk/api/2/foodbank/brent/", 
        "html": "https://www.givefood.org.uk/needs/at/brent/"
      }, 
      "slug": "brent"
    }, 
    "self": "https://www.givefood.org.uk/api/2/needs/39c77e7d/"
  }, 
  {
    "found": "2020-12-15T12:04:27.185Z", 
    "needs": "Custard\r\nTinned Fish\r\nPacket And Tinned Potatoes\r\nCoffee/tea\r\nTinned Fruit\r\nJams, Sauces, Etc.\r\nLong Life Juice (Apple/orange)", 
    "id": "f596df00", 
    "foodbank": {
      "name": "Newtownabbey", 
      "urls": {
        "self": "https://www.givefood.org.uk/api/2/foodbank/newtownabbey/", 
        "html": "https://www.givefood.org.uk/needs/at/newtownabbey/"
      }, 
      "slug": "newtownabbey"
    }, 
    "self": "https://www.givefood.org.uk/api/2/needs/f596df00/"
  }, 
  {
    "found": "2020-12-15T08:53:35.773Z", 
    "needs": "Sugar\r\nTinned Fruit\r\nJam\r\nCoffee\r\nDiluting Juice", 
    "id": "5c0c8439", 
    "foodbank": {
      "name": "Rutherglen & Cambuslang", 
      "urls": {
        "self": "https://www.givefood.org.uk/api/2/foodbank/rutherglen-cambuslang/", 
        "html": "https://www.givefood.org.uk/needs/at/rutherglen-cambuslang/"
      }, 
      "slug": "rutherglen-cambuslang"
    }, 
    "self": "https://www.givefood.org.uk/api/2/needs/5c0c8439/"
  }, 
  {
    "found": "2020-12-14T21:23:54.483Z", 
    "needs": "Tinned Salmon\r\nTinned Ham\r\nFace Masks\r\nLong-life Juice And Fruit Squash\r\nUHT Milk\r\nTinned Vegetables\r\nTinned Ready Meals\r\nCheese Crackers/crisps/twiglets Etc\r\nSugar\r\nCoffee\r\nSmall Jars Of Pasta Sauce", 
    "id": "b1e6a407", 
    "foodbank": {
      "name": "Uttlesford", 
      "urls": {
        "self": "https://www.givefood.org.uk/api/2/foodbank/uttlesford/", 
        "html": "https://www.givefood.org.uk/needs/at/uttlesford/"
      }, 
      "slug": "uttlesford"
    }, 
    "self": "https://www.givefood.org.uk/api/2/needs/b1e6a407/"
  }, 
  {
    "found": "2020-12-14T18:48:14.464Z", 
    "needs": "Tinned Tuna\r\nTinned Meats\r\nTinned Potatoes\r\nTinned Carrots\r\nTinned Peas\r\nPackets Of Biscuits\r\nCartons Of Milk\r\nCartons Of Juice\r\nLarge Size Nappies", 
    "id": "4b9926a1", 
    "foodbank": {
      "name": "Pontefract", 
      "urls": {
        "self": "https://www.givefood.org.uk/api/2/foodbank/pontefract/", 
        "html": "https://www.givefood.org.uk/needs/at/pontefract/"
      }, 
      "slug": "pontefract"
    }, 
    "self": "https://www.givefood.org.uk/api/2/needs/4b9926a1/"
  }, 
  {
    "found": "2020-12-14T18:31:33.708Z", 
    "needs": "Tins Of Baked Bean And Sausage\r\nTinned Meatballs\r\nJars Of Coffee\r\nTinned Sweetcorn", 
    "id": "13d75b43", 
    "foodbank": {
      "name": "Yeovil", 
      "urls": {
        "self": "https://www.givefood.org.uk/api/2/foodbank/yeovil/", 
        "html": "https://www.givefood.org.uk/needs/at/yeovil/"
      }, 
      "slug": "yeovil"
    }, 
    "self": "https://www.givefood.org.uk/api/2/needs/13d75b43/"
  }, 
  {
    "found": "2020-12-14T18:04:59.393Z", 
    "needs": "All Toiletries\r\nInstant Smash\r\nTinned Potatoes", 
    "id": "3cd861ad", 
    "foodbank": {
      "name": "Port Talbot", 
      "urls": {
        "self": "https://www.givefood.org.uk/api/2/foodbank/port-talbot/", 
        "html": "https://www.givefood.org.uk/needs/at/port-talbot/"
      }, 
      "slug": "port-talbot"
    }, 
    "self": "https://www.givefood.org.uk/api/2/needs/3cd861ad/"
  }, 
  {
    "found": "2020-12-14T17:23:05.601Z", 
    "needs": "Canned Fruit\r\nJams And Marmalades\r\nToilet Rolls\r\nRice Pudding\r\nMen's Deodorants\r\nCanned Potatoes\r\nMash\r\nClothes Washing Detergent\r\nWashing-up Liquid", 
    "id": "fc164693", 
    "foodbank": {
      "name": "Hart", 
      "urls": {
        "self": "https://www.givefood.org.uk/api/2/foodbank/hart/", 
        "html": "https://www.givefood.org.uk/needs/at/hart/"
      }, 
      "slug": "hart"
    }, 
    "self": "https://www.givefood.org.uk/api/2/needs/fc164693/"
  }, 
  {
    "found": "2020-12-14T17:04:08.120Z", 
    "needs": "Custard\r\nMarmalade\r\nTinned Potatoes\r\nSugar (1kg & 500g)\r\nTrifle Kits", 
    "id": "45ee59af", 
    "foodbank": {
      "name": "Rugby", 
      "urls": {
        "self": "https://www.givefood.org.uk/api/2/foodbank/rugby/", 
        "html": "https://www.givefood.org.uk/needs/at/rugby/"
      }, 
      "slug": "rugby"
    }, 
    "self": "https://www.givefood.org.uk/api/2/needs/45ee59af/"
  }, 
  {
    "found": "2020-12-14T16:34:47.509Z", 
    "needs": "Savoury Biscuits 150g\r\nChocolate Finger Biscuits\r\nChristmas Chocolate Biscuits, Any!\r\nChocolate Sweet Selection Boxes 250-350g\r\nPringles\r\nTinned Spaghetti\r\nPacks Of Juice 150ml\r\nPacket Cup-a-soup\r\nBags For Life", 
    "id": "d756dc8a", 
    "foodbank": {
      "name": "Farnborough", 
      "urls": {
        "self": "https://www.givefood.org.uk/api/2/foodbank/farnborough/", 
        "html": "https://www.givefood.org.uk/needs/at/farnborough/"
      }, 
      "slug": "farnborough"
    }, 
    "self": "https://www.givefood.org.uk/api/2/needs/d756dc8a/"
  }, 
  {
    "found": "2020-12-14T16:29:08.321Z", 
    "needs": "Savoury Biscuits & Crackers\r\nLong Life Fruit Juice And Squash\r\nReady Made Custard - Tins Or Cartons\r\nTomato Ketchup\r\nPeanut Butter, Honey & Jam\r\nVegetarian Chill & Curry\r\nCooking Oil - 250ml Or 500ml Sizes Please\r\nShower Gel, Hair Shampoo & Hand Wash\r\nLaundry Products - Powder, Liquid, Tablets (Small Sizes Please)", 
    "id": "bfd0ef5a", 
    "foodbank": {
      "name": "Ealing", 
      "urls": {
        "self": "https://www.givefood.org.uk/api/2/foodbank/ealing/", 
        "html": "https://www.givefood.org.uk/needs/at/ealing/"
      }, 
      "slug": "ealing"
    }, 
    "self": "https://www.givefood.org.uk/api/2/needs/bfd0ef5a/"
  }, 
  {
    "found": "2020-12-14T16:04:57.586Z", 
    "needs": "Tinned Curries\r\nTinned Stews\r\nFairy Liquid\r\nHouse Cleaning Products", 
    "id": "f05ad1b4", 
    "foodbank": {
      "name": "Lisburn", 
      "urls": {
        "self": "https://www.givefood.org.uk/api/2/foodbank/lisburn/", 
        "html": "https://www.givefood.org.uk/needs/at/lisburn/"
      }, 
      "slug": "lisburn"
    }, 
    "self": "https://www.givefood.org.uk/api/2/needs/f05ad1b4/"
  }, 
  {
    "found": "2020-12-14T15:53:36.617Z", 
    "needs": "Sweet Spreads\r\nFruit Juice\r\nRice Pudding\r\nDesserts\r\nCustard\r\nTinned Spaghetti\r\nTinned Fruit\r\nSoap\r\nShampoo\r\nToothbrushes", 
    "id": "3c5864e0", 
    "foodbank": {
      "name": "Basingstoke", 
      "urls": {
        "self": "https://www.givefood.org.uk/api/2/foodbank/basingstoke/", 
        "html": "https://www.givefood.org.uk/needs/at/basingstoke/"
      }, 
      "slug": "basingstoke"
    }, 
    "self": "https://www.givefood.org.uk/api/2/needs/3c5864e0/"
  }, 
  {
    "found": "2020-12-14T15:38:32.939Z", 
    "needs": "Fruit Squash\r\nShaving Foam\r\nDry Cat Food\r\nLong Life Milk\r\nMeat Soups\r\nRice Pudding\r\nTins Of Meat\r\nTinned Potatoes\r\nTinned Sweetcorn/green Veg\r\nTinned Carrots\r\nCranberry Sauce\r\nGravy Granules\r\nStuffing\r\nChristmas Pudding\r\nMince Pies\r\nTinned Custard/tinned Cream\r\nTinned Fruit\r\nPackets Of Christmassy Biscuits\r\nBox Of Chocolates\r\nSavoury Nibbles\r\nChristmas Cake Or Chocolate Log\r\nSoft Drinks (No Alcohol Please)", 
    "id": "5fc913ea", 
    "foodbank": {
      "name": "Penryn & Falmouth", 
      "urls": {
        "self": "https://www.givefood.org.uk/api/2/foodbank/penryn-falmouth/", 
        "html": "https://www.givefood.org.uk/needs/at/penryn-falmouth/"
      }, 
      "slug": "penryn-falmouth"
    }, 
    "self": "https://www.givefood.org.uk/api/2/needs/5fc913ea/"
  }, 
  {
    "found": "2020-12-14T15:23:10.378Z", 
    "needs": "Coffee\r\nTinned Potatoes\r\nTinned Fish\r\nTinned Vegetables\r\nTinned Meat\r\nTinned Custard\r\nTinned Rice Pudding\r\nDilute/long Life Juice", 
    "id": "b4eadba2", 
    "foodbank": {
      "name": "Leeds South & East", 
      "urls": {
        "self": "https://www.givefood.org.uk/api/2/foodbank/leeds-south-east/", 
        "html": "https://www.givefood.org.uk/needs/at/leeds-south-east/"
      }, 
      "slug": "leeds-south-east"
    }, 
    "self": "https://www.givefood.org.uk/api/2/needs/b4eadba2/"
  }, 
  {
    "found": "2020-12-14T15:17:32.307Z", 
    "needs": "Instant Coffee (100g)\r\nLong Life Fruit Juice\r\nTinned Potatoes\r\nSmall Bags Of Sugar (500g)\r\nShampoo\r\nDeodorants (Male And Female)\r\nDisposable Nappies (Ideally Sizes 4, 5 Or 6)", 
    "id": "a8f5bf08", 
    "foodbank": {
      "name": "Yiewsley & West Drayton", 
      "urls": {
        "self": "https://www.givefood.org.uk/api/2/foodbank/yiewsley-west-drayton/", 
        "html": "https://www.givefood.org.uk/needs/at/yiewsley-west-drayton/"
      }, 
      "slug": "yiewsley-west-drayton"
    }, 
    "self": "https://www.givefood.org.uk/api/2/needs/a8f5bf08/"
  }, 
  {
    "found": "2020-12-14T14:36:37.875Z", 
    "needs": "Nothing", 
    "id": "18158aac", 
    "foodbank": {
      "name": "Eastbourne", 
      "urls": {
        "self": "https://www.givefood.org.uk/api/2/foodbank/eastbourne/", 
        "html": "https://www.givefood.org.uk/needs/at/eastbourne/"
      }, 
      "slug": "eastbourne"
    }, 
    "self": "https://www.givefood.org.uk/api/2/needs/18158aac/"
  }, 
  {
    "found": "2020-12-14T13:19:13.272Z", 
    "needs": "Supermarket Gift Cards\r\nSandwich Paste\r\nTinned Cold Meat\r\nInstant Mash\r\nSugar\r\nChocolates\r\nChildren's Sweets\r\nCrisps\r\nDry Dog Food\r\nCat Food\r\nCooking Oil\r\nMixed Herbs\r\nSalt\r\nTomato Puree\r\nDeodorant For Men\r\nWashing Powder - Small Packs\r\nAnti-bac Spray And Wipes\r\nKitchen Roll\r\nAdult Toothbrushes\r\nToothpaste\r\nHair Conditioner\r\nDisposable Razors\r\nShaving Foam\r\nCleaning Cloths/sponges", 
    "id": "7f71bd86", 
    "foodbank": {
      "name": "Worcester", 
      "urls": {
        "self": "https://www.givefood.org.uk/api/2/foodbank/worcester/", 
        "html": "https://www.givefood.org.uk/needs/at/worcester/"
      }, 
      "slug": "worcester"
    }, 
    "self": "https://www.givefood.org.uk/api/2/needs/7f71bd86/"
  }, 
  {
    "found": "2020-12-14T11:32:44.565Z", 
    "needs": "Washing Powder\r\nWashing Up Liquid", 
    "id": "b936d13c", 
    "foodbank": {
      "name": "Fallowfield & Withington", 
      "urls": {
        "self": "https://www.givefood.org.uk/api/2/foodbank/fallowfield-withington/", 
        "html": "https://www.givefood.org.uk/needs/at/fallowfield-withington/"
      }, 
      "slug": "fallowfield-withington"
    }, 
    "self": "https://www.givefood.org.uk/api/2/needs/b936d13c/"
  }, 
  {
    "found": "2020-12-14T11:05:04.729Z", 
    "needs": "Long-life Sponge Pudding\r\nInstant Mash/tinned Potatoes\r\nRice Pudding\r\nLong-life Juice\r\nJars Of Instant Coffee\r\nTinned Meat\r\nTeabags (40s/80s)\r\nChocolate Treats For Children\r\nTinned Fruit", 
    "id": "f42bd600", 
    "foodbank": {
      "name": "Cirencester", 
      "urls": {
        "self": "https://www.givefood.org.uk/api/2/foodbank/cirencester/", 
        "html": "https://www.givefood.org.uk/needs/at/cirencester/"
      }, 
      "slug": "cirencester"
    }, 
    "self": "https://www.givefood.org.uk/api/2/needs/f42bd600/"
  }, 
  {
    "found": "2020-12-14T09:22:48.389Z", 
    "needs": "UHT Fruit Juice 1l\r\nTinned Tomatoes\r\nTinned Potatoes\r\nTinned Meat\r\nSponge Puddings\r\nTinned Fruit\r\nSugar 500g Only\r\nSavoury Snacks\r\nShower Gel\r\nBaby Wipes\r\nShaving Foam\r\nHousehold Cleaning Sprays", 
    "id": "9297f97c", 
    "foodbank": {
      "name": "Cobham Area", 
      "urls": {
        "self": "https://www.givefood.org.uk/api/2/foodbank/cobham-area/", 
        "html": "https://www.givefood.org.uk/needs/at/cobham-area/"
      }, 
      "slug": "cobham-area"
    }, 
    "self": "https://www.givefood.org.uk/api/2/needs/9297f97c/"
  }, 
  {
    "found": "2020-12-13T12:13:33.730Z", 
    "needs": "Long Life Sponge Pudding", 
    "id": "2e9bc941", 
    "foodbank": {
      "name": "Caterham", 
      "urls": {
        "self": "https://www.givefood.org.uk/api/2/foodbank/caterham/", 
        "html": "https://www.givefood.org.uk/needs/at/caterham/"
      }, 
      "slug": "caterham"
    }, 
    "self": "https://www.givefood.org.uk/api/2/needs/2e9bc941/"
  }, 
  {
    "found": "2020-12-13T11:50:37.383Z", 
    "needs": "Tinned Custard\r\nTinned Peas And Carrots And Potatoes\r\nSponge Puddings\r\nTinned Meat (Hot Dogs, Stewing Steak Etc)\r\nTinned Ham\r\nRice (Dry)\r\nBiscuits\r\nTuna\r\nToilet Rolls\r\nBaby Wipes", 
    "id": "c52ae2c8", 
    "foodbank": {
      "name": "Alton", 
      "urls": {
        "self": "https://www.givefood.org.uk/api/2/foodbank/alton/", 
        "html": "https://www.givefood.org.uk/needs/at/alton/"
      }, 
      "slug": "alton"
    }, 
    "self": "https://www.givefood.org.uk/api/2/needs/c52ae2c8/"
  }, 
  {
    "found": "2020-12-13T11:44:15.408Z", 
    "needs": "Small Packets Of Tea Bags (40s And 80s)\r\nSugar (500g Bags)\r\nGender Neutral Roll On Deodorants\r\nDisposable Razors\r\nSingle Wrapped/boxes Adult Toothbrushes\r\nTinned Meat (Ham, Corned Beef, Chopped Pork, Meat Chunks In Sauce)\r\nTinned Fruit\r\nTinned Or Carton Custard\r\nUHT Whole Milk (Blue)\r\nInstant Mash\r\nInstant Hot Chocolate\r\nInstant Coffee\r\nJam/honey/peanut Butter\r\nLong Life Fruit Juice\r\nTinned Spaghetti\r\nTinned Rice Pudding\r\nPasta Sauces\r\nSquash\r\nRice\r\nUHT Semi Skimmed Milk (Green)\r\nShampoo, Shower Gel, Single Soap Bars\r\nToothpaste\r\nCrisps\r\nSturdy Bags For Life", 
    "id": "710237d2", 
    "foodbank": {
      "name": "B30", 
      "urls": {
        "self": "https://www.givefood.org.uk/api/2/foodbank/b30/", 
        "html": "https://www.givefood.org.uk/needs/at/b30/"
      }, 
      "slug": "b30"
    }, 
    "self": "https://www.givefood.org.uk/api/2/needs/710237d2/"
  }, 
  {
    "found": "2020-12-13T00:15:46.369Z", 
    "needs": "Savoury Biscuits 150g\r\nChocolate Finger Biscuits\r\nChristmas Chocolate Biscuits, Any!\r\nChristmas Mince Pies\r\nAdult Boxed Confectionery 250-350g\r\nPringles\r\nTinned Spaghetti\r\nPacks Of Juice 150ml\r\nPacket Cup-a-soup\r\nBags For Life", 
    "id": "da11f608", 
    "foodbank": {
      "name": "Farnborough", 
      "urls": {
        "self": "https://www.givefood.org.uk/api/2/foodbank/farnborough/", 
        "html": "https://www.givefood.org.uk/needs/at/farnborough/"
      }, 
      "slug": "farnborough"
    }, 
    "self": "https://www.givefood.org.uk/api/2/needs/da11f608/"
  }, 
  {
    "found": "2020-12-12T18:00:09.897Z", 
    "needs": "Strong Supermarket Bags Or Bags For Life\r\nTinned Ham\r\nTinned Salmon\r\nTinned Potatoes\r\nTinned Carrots & Peas\r\nTinned Fruit\r\nTinned Custard\r\nTins Of Meat Casserole (Ideally 2/3 Tins Same Thing For Large Families)\r\n10 Co-op Or Sainsburys Vouchers (To Go In Xmas Parcels To Buy Fresh Meat)", 
    "id": "24f45ede", 
    "foodbank": {
      "name": "Loveworks", 
      "urls": {
        "self": "https://www.givefood.org.uk/api/2/foodbank/loveworks/", 
        "html": "https://www.givefood.org.uk/needs/at/loveworks/"
      }, 
      "slug": "loveworks"
    }, 
    "self": "https://www.givefood.org.uk/api/2/needs/24f45ede/"
  }, 
  {
    "found": "2020-12-12T15:43:05.939Z", 
    "needs": "Hot Chocolate\r\nCondiments- Cranberry Sauce/ Stuffing Packs/gravy\r\nChristmas Cake/chocolate/ Puddings (Non Alcoholic)\r\nBaked Beans\r\nTinned Tomatoes\r\nRice", 
    "id": "de82aca5", 
    "foodbank": {
      "name": "North Enfield", 
      "urls": {
        "self": "https://www.givefood.org.uk/api/2/foodbank/north-enfield/", 
        "html": "https://www.givefood.org.uk/needs/at/north-enfield/"
      }, 
      "slug": "north-enfield"
    }, 
    "self": "https://www.givefood.org.uk/api/2/needs/de82aca5/"
  }, 
  {
    "found": "2020-12-12T12:37:32.450Z", 
    "needs": "Washing Detergent\r\nShaving Foam/gel\r\nTinned Meat\r\nCustard\r\nRice Pudding\r\nTinned Fruit\r\nSponge Puddings\r\nJam\r\nSmall Jars Of Coffee\r\nShampoo & Conditioner\r\nDeodorant\r\nToilet Rolls\r\nTinned Potatoes\r\nTinned Spaghetti\r\nCrisps\r\nChutney\r\nStuffing\r\nChristmas Cake\r\nChristmassy Cake Items/sweet Snacks\r\n'Soft Drinks' (Not Chilled)", 
    "id": "0b15ec09", 
    "foodbank": {
      "name": "Brecon", 
      "urls": {
        "self": "https://www.givefood.org.uk/api/2/foodbank/brecon/", 
        "html": "https://www.givefood.org.uk/needs/at/brecon/"
      }, 
      "slug": "brecon"
    }, 
    "self": "https://www.givefood.org.uk/api/2/needs/0b15ec09/"
  }, 
  {
    "found": "2020-12-12T10:25:25.425Z", 
    "needs": "Tea\r\nCoffee\r\nUHT Milk\r\nSpam\r\nCheese\r\nYogurts\r\nSoap\r\nAnti Bac Wipes\r\nNappies\r\nBaby Milk\r\nCordial\r\nFruit Juice\r\nPot Noodles\r\nToilet Roll\r\nBaby Food\r\nSanitary Supplies\r\nShaving", 
    "id": "361027e4", 
    "foodbank": {
      "name": "Brandlesholme", 
      "urls": {
        "self": "https://www.givefood.org.uk/api/2/foodbank/brandlesholme/", 
        "html": "https://www.givefood.org.uk/needs/at/brandlesholme/"
      }, 
      "slug": "brandlesholme"
    }, 
    "self": "https://www.givefood.org.uk/api/2/needs/361027e4/"
  }, 
  {
    "found": "2020-12-12T09:39:13.259Z", 
    "needs": "Pot Noodles\r\nSmall Jars Of Coffee\r\nUHT Fruit Juice (1 Litre)\r\nSavoury Biscuits Eg Ryvita", 
    "id": "bdca1a68", 
    "foodbank": {
      "name": "Bradford on Avon", 
      "urls": {
        "self": "https://www.givefood.org.uk/api/2/foodbank/bradford-on-avon/", 
        "html": "https://www.givefood.org.uk/needs/at/bradford-on-avon/"
      }, 
      "slug": "bradford-on-avon"
    }, 
    "self": "https://www.givefood.org.uk/api/2/needs/bdca1a68/"
  }, 
  {
    "found": "2020-12-11T23:22:26.608Z", 
    "needs": "Feminine Hygiene - Tampons And Towels, Any Size\r\nShaving Gel /Foam\r\nKetchup And Brown Sauce\r\nToilet Rolls\r\nTinned Mixed Vegetables\r\nSponge Puddings\r\nTinned Potatoes\r\nSmall Bottles Of Cooking Oil", 
    "id": "7ab173af", 
    "foodbank": {
      "name": "Chichester District", 
      "urls": {
        "self": "https://www.givefood.org.uk/api/2/foodbank/chichester-district/", 
        "html": "https://www.givefood.org.uk/needs/at/chichester-district/"
      }, 
      "slug": "chichester-district"
    }, 
    "self": "https://www.givefood.org.uk/api/2/needs/7ab173af/"
  }, 
  {
    "found": "2020-12-11T21:16:15.070Z", 
    "needs": "Pasta Sauce\r\nLong Life Milk\r\nTinned Meat\r\nMeat Pies\r\nCustard\r\nSmall Washing Powder", 
    "id": "270ab7ca", 
    "foodbank": {
      "name": "Wokingham", 
      "urls": {
        "self": "https://www.givefood.org.uk/api/2/foodbank/wokingham/", 
        "html": "https://www.givefood.org.uk/needs/at/wokingham/"
      }, 
      "slug": "wokingham"
    }, 
    "self": "https://www.givefood.org.uk/api/2/needs/270ab7ca/"
  }
]